lakeapi/__init__.py
lakeapi/_cache.py
lakeapi/_config.py
lakeapi/_data_types.py
lakeapi/_describe.py
lakeapi/_fs.py
lakeapi/_read.py
lakeapi/_read_parquet.py
lakeapi/_utils.py
lakeapi/exceptions.py
lakeapi/main.py
lakeapi/orderbook.py
lakeapi/response_stream.py
lakeapi/test.py
lakeapi-0.22.2.dist-info/AUTHORS.rst
lakeapi-0.22.2.dist-info/LICENSE
lakeapi-0.22.2.dist-info/METADATA
lakeapi-0.22.2.dist-info/NOTICE.rst
lakeapi-0.22.2.dist-info/WHEEL
lakeapi-0.22.2.dist-info/entry_points.txt
lakeapi-0.22.2.dist-info/top_level.txt
lakeapi-0.22.2.dist-info/RECORD
