Metadata-Version: 2.1
Name: lakeapi
Version: 0.22.2
Summary: API for accessing Lake crypto market data
Home-page: https://github.com/crypto-lake/lake-api
Author: Jan Skoda
Author-email: skoda@jskoda.cz
License: Apache 2 license
Keywords: lakeapi
Classifier: Development Status :: 2 - Pre-Alpha
Classifier: Intended Audience :: Developers
Classifier: License :: OSI Approved :: Apache Software License
Classifier: Natural Language :: English
Classifier: Programming Language :: Python :: 3
Classifier: Programming Language :: Python :: 3.7
Classifier: Programming Language :: Python :: 3.8
Classifier: Programming Language :: Python :: 3.9
Classifier: Programming Language :: Python :: 3.10
Classifier: Programming Language :: Python :: 3.11
Classifier: Programming Language :: Python :: 3.12
Requires-Python: >=3.7
License-File: LICENSE
License-File: NOTICE.rst
License-File: AUTHORS.rst
Requires-Dist: pandas <3,>=1.0.5
Requires-Dist: boto3 <2,>=1.24
Requires-Dist: cachetools-ext <0.1.0,>=0.0.8
Requires-Dist: botocache <0.1.0,>=0.0.4
Requires-Dist: joblib <1.5.0,>=1.0.0
Requires-Dist: tqdm <5,>=4
Requires-Dist: pyarrow >=2.0.0
Requires-Dist: aws-requests-auth ==0.4.3
Requires-Dist: numba
Requires-Dist: typing-extensions <5,>=4.0 ; python_version < "3.8"
